sshkey/__init__.py
sshkey/public.py
tests/__init__.py
tests/test_public.py
sshkey-0.1.0.dist-info/LICENSE
sshkey-0.1.0.dist-info/METADATA
sshkey-0.1.0.dist-info/WHEEL
sshkey-0.1.0.dist-info/top_level.txt
sshkey-0.1.0.dist-info/RECORD
