Metadata-Version: 2.1
Name: sshkey
Version: 0.1.0
Summary: SSH key management utility
Home-page: https://github.com/yosida95/python-sshkey
Author: Kohei YOSHIDA
Author-email: kohei@yosida95.com
License: BSD-3-Clause
Platform: UNKNOWN
Classifier: Development Status :: 4 - Beta
Classifier: Intended Audience :: Developers
Classifier: License :: OSI Approved :: BSD License
Classifier: Operating System :: OS Independent
Classifier: Programming Language :: Python
Classifier: Programming Language :: Python :: 3
Classifier: Topic :: Security
Classifier: Topic :: Software Development :: Libraries :: Python Modules
Requires-Python: >= 3.6
